AUTHORS
LICENSE
MANIFEST.in
README.rst
setup.cfg
setup.py
sphinxcontrib/__init__.py
sphinxcontrib/rawfiles.py
sphinxcontrib_rawfiles.egg-info/PKG-INFO
sphinxcontrib_rawfiles.egg-info/SOURCES.txt
sphinxcontrib_rawfiles.egg-info/dependency_links.txt
sphinxcontrib_rawfiles.egg-info/namespace_packages.txt
sphinxcontrib_rawfiles.egg-info/not-zip-safe
sphinxcontrib_rawfiles.egg-info/requires.txt
sphinxcontrib_rawfiles.egg-info/top_level.txt