Metadata-Version: 1.0
Name: sphinxcontrib-rawfiles
Version: 0.1
Summary: Sphinx "rawfiles" extension
Home-page: http://bitbucket.org/birkenfeld/sphinx-contrib
Author: Takumi IINO
Author-email: trot.thunder@gmail.com
License: BSD
Download-URL: http://pypi.python.org/pypi/sphinxcontrib-rawfiles
Platform: any
Classifier: Development Status :: 4 - Beta
Classifier: Environment :: Console
Classifier: Environment :: Web Environment
Classifier: Intended Audience :: Developers
Classifier: License :: OSI Approved :: BSD License
Classifier: Operating System :: OS Independent
Classifier: Programming Language :: Python
Classifier: Topic :: Documentation
Classifier: Topic :: Utilities
